boterview/__init__.py
boterview/chat/chat.py
boterview/cli/cli.py
boterview/cli/commands/generate.py
boterview/cli/commands/parse.py
boterview/cli/commands/preview.py
boterview/cli/commands/run.py
boterview/context/app.py
boterview/context/bot.py
boterview/context/content.py
boterview/context/path.py
boterview/context/persistence.py
boterview/helpers/authentication.py
boterview/helpers/chat.py
boterview/helpers/storage.py
boterview/helpers/utils.py
boterview/models/api/code.py
boterview/models/api/participant.py
boterview/models/api/secret.py
boterview/models/database/base.py
boterview/models/database/conversation.py
boterview/models/database/participant.py
boterview/server/api.py
boterview/server/sever.py
boterview/services/boterview/boterview.py
boterview/services/boterview/closing.py
boterview/services/boterview/code.py
boterview/services/boterview/condition.py
boterview/services/boterview/conversation.py
boterview/services/boterview/counter.py
boterview/services/boterview/guide.py
boterview/services/boterview/interview.py
boterview/services/boterview/introduction.py
boterview/services/boterview/participant.py
boterview/services/boterview/printable.py
boterview/services/boterview/prompt.py
boterview/services/boterview/protocol.py
boterview/services/boterview/question.py
boterview/services/boterview/study.py
boterview/services/configuration/configuration.py
boterview/services/configuration/template.py
boterview/services/ui/element.py
boterview/services/ui/footer.py
boterview/services/ui/page.py
boterview/services/ui/ui.py
boterview/frontend/chat/.chainlit/config.toml
boterview/frontend/chat/.chainlit/translations/bn.json
boterview/frontend/chat/.chainlit/translations/en-US.json
boterview/frontend/chat/.chainlit/translations/gu.json
boterview/frontend/chat/.chainlit/translations/he-IL.json
boterview/frontend/chat/.chainlit/translations/hi.json
boterview/frontend/chat/.chainlit/translations/ja.json
boterview/frontend/chat/.chainlit/translations/kn.json
boterview-1.3.0.dist-info/METADATA
boterview-1.3.0.dist-info/WHEEL
boterview-1.3.0.dist-info/entry_points.txt
boterview-1.3.0.dist-info/licenses/LICENSE
boterview-1.3.0.dist-info/RECORD
