Metadata-Version: 2.4
Name: boterview
Version: 1.3.0
Summary: Effortlessly conduct chatbot-based interviews with customizable protocols and randomized condition assignments, tailored for social science research.
Project-URL: Homepage, https://boterview.dev
Project-URL: Repository, https://github.com/mihaiconstantin/boterview
Project-URL: Issues, https://github.com/mihaiconstantin/boterview/issues
Project-URL: Changelog, https://github.com/mihaiconstantin/boterview/blob/main/CHANGELOG.md
Author-email: Mihai Constantin <mihai@mihaiconstantin.com>
Maintainer-email: Mihai Constantin <mihai@mihaiconstantin.com>
License-Expression: MIT
License-File: LICENSE
Keywords: LLM,chatbot,interview,research,social science,survey
Classifier: Development Status :: 5 - Production/Stable
Classifier: Intended Audience :: Education
Classifier: Intended Audience :: Science/Research
Classifier: Operating System :: OS Independent
Classifier: Programming Language :: Python :: 3.10
Classifier: Topic :: Communications :: Chat
Classifier: Topic :: Education
Classifier: Topic :: Sociology
Requires-Python: >=3.10
Requires-Dist: chainlit==2.4.400
Requires-Dist: click
Requires-Dist: fastapi
Requires-Dist: openai
Requires-Dist: peewee
Requires-Dist: pydantic
Requires-Dist: pyjwt
Requires-Dist: python-dotenv
Requires-Dist: tomli
Requires-Dist: uvicorn
